AUTHORS.rst
CHANGELOG.rst
INSTALL.rst
LICENSE.rst
MANIFEST.in
README.rst
TODO.rst
requirements.txt
setup.py
bin/smalisca
smalisca/VERSION
smalisca/__init__.py
smalisca.egg-info/PKG-INFO
smalisca.egg-info/SOURCES.txt
smalisca.egg-info/dependency_links.txt
smalisca.egg-info/requires.txt
smalisca.egg-info/top_level.txt
smalisca/analysis/__init__.py
smalisca/analysis/analysis_base.py
smalisca/analysis/analysis_json.py
smalisca/analysis/analysis_shell.py
smalisca/analysis/analysis_sqlite.py
smalisca/controller/__init__.py
smalisca/controller/controller_analyzer.py
smalisca/controller/controller_base.py
smalisca/controller/controller_parser.py
smalisca/controller/controller_web.py
smalisca/core/__init__.py
smalisca/core/smalisca_analysis.py
smalisca/core/smalisca_app.py
smalisca/core/smalisca_config.py
smalisca/core/smalisca_logging.py
smalisca/core/smalisca_main.py
smalisca/core/smalisca_module.py
smalisca/modules/__init__.py
smalisca/modules/module_graph.py
smalisca/modules/module_smali_parser.py
smalisca/modules/module_sql_models.py
smalisca/modules/web/__init__.py
smalisca/modules/web/module_web.py