Metadata-Version: 1.1
Name: smalisca
Version: 0.2
Summary: Static code analysis tool for Smali files
Home-page: http://github.com/dorneanu/smalisca
Author: Victor Dorneanu
Author-email: info@dornea.nu
License: MIT
Download-URL: https://github.com/dorneanu/smalisca/archive/0.2.tar.gz
Keywords: cli smali sca
Platform: UNKNOWN
Classifier: Programming Language :: Python
Classifier: Natural Language :: English
Classifier: Topic :: Security
Classifier: Topic :: Software Development :: Libraries :: Java Libraries
Classifier: Operating System :: OS Independent
Classifier: License :: OSI Approved :: MIT License
